Metadata-Version: 2.1
Name: stokespy
Version: 0.5.0
Summary: Open-source (future) SunPy affiliated package for the visualization and analyis of solar spectropolarimetric data and inversion results.
Home-page: 
Author: Gabriel Dima
Author-email: gdima@ucar.edu
License: BSD 3-Clause
Platform: UNKNOWN
Requires-Python: >=3.7
Provides-Extra: test
Provides-Extra: docs
Provides-Extra: dev
Provides-Extra: all
License-File: LICENSE.rst
